bootleg_jwt/__init__.py
bootleg_jwt/funcs.py
bootleg_jwt/main.py
bootleg_jwt/messages.py
bootleg_jwt/schema.py
bootleg_jwt-0.3.0.dist-info/LICENSE
bootleg_jwt-0.3.0.dist-info/METADATA
bootleg_jwt-0.3.0.dist-info/WHEEL
bootleg_jwt-0.3.0.dist-info/top_level.txt
bootleg_jwt-0.3.0.dist-info/RECORD
