Metadata-Version: 2.1
Name: bootleg-jwt
Version: 0.3.0
Summary: Sign tokens with blake2b, then verify them.
Home-page: https://github.com/freyjagp/bootleg-jwt
Author: Freyja Odinthrir
Project-URL: Bug Reports, https://github.com/freyjagp/bootleg-jwt/issues
Project-URL: Source, https://github.com/freyjagp/bootleg-jwt/
Keywords: cryptography,tokens,hashing
Classifier: Development Status :: 4 - Beta
Classifier: Intended Audience :: Developers
Classifier: License :: OSI Approved :: MIT License
Classifier: Programming Language :: Python :: 3.10
Classifier: Programming Language :: Python :: 3 :: Only
Classifier: Natural Language :: English
Classifier: Topic :: Internet :: WWW/HTTP :: Session
Classifier: Topic :: Security
Classifier: Topic :: Security :: Cryptography
Classifier: Topic :: Software Development :: Libraries
Classifier: Topic :: Software Development :: Libraries :: Python Modules
Requires-Python: >=3.10, <4
License-File: LICENSE
Requires-Dist: pydantic
Requires-Dist: python-decouple
Requires-Dist: cryptography
